<?xml version="1.0" encoding="UTF-8"?><record_update table="sp_instance">
    <sp_instance action="INSERT_OR_UPDATE">
        <active>true</active>
        <class_name/>
        <color>default</color>
        <css/>
        <glyph/>
        <id/>
        <order>1</order>
        <roles/>
        <short_description/>
        <size>md</size>
        <sp_column display_value="1">9d79ab38db84bb0016a5f40b0c961905</sp_column>
        <sp_widget display_value="Wow Welcome">76e2fdfcdb27d78087e2f3de3b961939</sp_widget>
        <sys_class_name>sp_instance</sys_class_name>
        <sys_created_by>admin</sys_created_by>
        <sys_created_on>2020-02-25 15:43:03</sys_created_on>
        <sys_customer_update>false</sys_customer_update>
        <sys_id>b619ceff1b870010723ded3abc4bcb01</sys_id>
        <sys_mod_count>3</sys_mod_count>
        <sys_name/>
        <sys_package display_value="Wow Portal" source="x_mono2_wow">c22adc75dba633400ef45682ca961996</sys_package>
        <sys_policy/>
        <sys_replace_on_upgrade>false</sys_replace_on_upgrade>
        <sys_scope display_value="Wow Portal">c22adc75dba633400ef45682ca961996</sys_scope>
        <sys_update_name>sp_instance_b619ceff1b870010723ded3abc4bcb01</sys_update_name>
        <sys_updated_by>Warren</sys_updated_by>
        <sys_updated_on>2020-03-19 12:26:46</sys_updated_on>
        <title/>
        <url/>
        <widget_parameters><![CDATA[{
	"message": {
		"value": "Welcome to the End User Portal",
		"displayValue": "Welcome to the End User Portal"
	},
	"image": {
		"value": "d92276f2dbfe7b00b62a80e2399619f7",
		"displayValue": "jumping_people.png"
	},
	"justify": {
		"value": "left",
		"displayValue": "left"
	},
	"reducedHeight": {
		"value": "true",
		"displayValue": "true"
	},
	"showAdvert": {
		"value": "false",
		"displayValue": "false"
	},
	"enableParallax": {
		"value": "true",
		"displayValue": "true"
	}
}]]></widget_parameters>
    </sp_instance>
    <sys_translated_text action="delete_multiple" query="documentkey=b619ceff1b870010723ded3abc4bcb01"/>
</record_update>
